{
    "data":[
        {
            "value": 21,
            "category": "a"
        },
        {
            "value": 42,
            "category": "b"
        },
        {
            "value": 43,
            "category": "c"
        },
        {
            "value": 5,
            "category": "d"
        },
        {
            "value": 26,
            "category": "e"
        },
        {
            "value": 7,
            "category": "f"
        },
        {
            "value": 10,
            "category": "l"
        },
        {
            "value": 18,
            "category": "s"
        },
        {
            "value": 85,
            "category": "x"
        }
    ]

}